<?xml version="1.0"?>
<annotation>
<folder>data</folder>
<filename>elk-alces-alces-droppings-forest-elk-alces-alces-droppings-forest-april-belarus-246428819.jpg</filename>
<path/>
<source>
<database>Unknown</database>
</source>
<size>
<width>800</width>
<height>534</height>
<depth>3</depth>
</size>
<segmented>0</segmented>
<object>
<name>Elk</name>
<pose>Unspecified</pose>
<truncated>0</truncated>
<occluded>0</occluded>
<difficult>0</difficult>
<bndbox>
<xmin>168</xmin>
<ymin>96</ymin>
<xmax>716</xmax>
<ymax>381</ymax>
</bndbox>
</object>
</annotation>